jsemulator/__init__.py
jsemulator/base.py
jsemulator/evaljs.py
jsemulator/node_import.py
jsemulator/pyjs.py
jsemulator/constructors/__init__.py
jsemulator/constructors/jsarray.py
jsemulator/constructors/jsarraybuffer.py
jsemulator/constructors/jsboolean.py
jsemulator/constructors/jsdate.py
jsemulator/constructors/jsfloat32array.py
jsemulator/constructors/jsfloat64array.py
jsemulator/constructors/jsfunction.py
jsemulator/constructors/jsint16array.py
jsemulator/constructors/jsint32array.py
jsemulator/constructors/jsint8array.py
jsemulator/constructors/jsmath.py
jsemulator/constructors/jsnumber.py
jsemulator/constructors/jsobject.py
jsemulator/constructors/jsregexp.py
jsemulator/constructors/jsstring.py
jsemulator/constructors/jsuint16array.py
jsemulator/constructors/jsuint32array.py
jsemulator/constructors/jsuint8array.py
jsemulator/constructors/jsuint8clampedarray.py
jsemulator/constructors/time_helpers.py
jsemulator/es6/__init__.py
jsemulator/es6/babel.py
jsemulator/host/__init__.py
jsemulator/host/console.py
jsemulator/host/jseval.py
jsemulator/host/jsfunctions.py
jsemulator/internals/__init__.py
jsemulator/internals/base.py
jsemulator/internals/byte_trans.py
jsemulator/internals/code.py
jsemulator/internals/conversions.py
jsemulator/internals/desc.py
jsemulator/internals/fill_space.py
jsemulator/internals/func_utils.py
jsemulator/internals/gen.py
jsemulator/internals/opcodes.py
jsemulator/internals/operations.py
jsemulator/internals/seval.py
jsemulator/internals/simplex.py
jsemulator/internals/space.py
jsemulator/internals/speed.py
jsemulator/internals/trans_utils.py
jsemulator/internals/constructors/__init__.py
jsemulator/internals/constructors/jsarray.py
jsemulator/internals/constructors/jsboolean.py
jsemulator/internals/constructors/jsconsole.py
jsemulator/internals/constructors/jsdate.py
jsemulator/internals/constructors/jsfunction.py
jsemulator/internals/constructors/jsmath.py
jsemulator/internals/constructors/jsnumber.py
jsemulator-0.7.4.dist-info/LICENSE.md
jsemulator-0.7.4.dist-info/METADATA
jsemulator-0.7.4.dist-info/WHEEL
jsemulator-0.7.4.dist-info/top_level.txt
jsemulator-0.7.4.dist-info/RECORD
