Metadata-Version: 2.2
Name: jsemulator
Version: 0.7.4
Summary: JavaScript to Python Translator & JavaScript interpreter written in 100% pure Python.
Author: Blake Foster
Author-email: blakehulsey@gmail.com
License: MIT
License-File: LICENSE.md
Requires-Dist: tzlocal>=1.2
Requires-Dist: six>=1.10
Requires-Dist: jsparser>=2.7.3
Dynamic: author
Dynamic: author-email
Dynamic: description
Dynamic: license
Dynamic: requires-dist
Dynamic: summary
